custom_openai/__init__.py
custom_openai/client.py
flashquery-0.8.0.dist-info/licenses/LICENSE
flashquery-0.8.0.dist-info/METADATA
flashquery-0.8.0.dist-info/WHEEL
flashquery-0.8.0.dist-info/top_level.txt
flashquery-0.8.0.dist-info/RECORD
