Metadata-Version: 2.4
Name: flashquery
Version: 0.8.0
Summary: A custom wrapper for the Langchain Python package with modified response handling
Author-email: "FlashQuery.AI (Planorama Labs)" <contact@flashquery.ai>
License: MIT
Project-URL: Homepage, https://bitbucket.org/planorama-design/custom_openai_package
Keywords: openai,wrapper,api,chatgpt
Classifier: Programming Language :: Python :: 3
Classifier: License :: OSI Approved :: MIT License
Classifier: Operating System :: OS Independent
Requires-Python: >=3.8
License-File: LICENSE
Requires-Dist: langchain-anthropic>=1.0.0
Requires-Dist: langchain-aws>=1.0.0
Requires-Dist: langchain_openai>=1.0.0
Requires-Dist: langchain-ibm>=1.0.0
Dynamic: license-file
